mandelshtam/__init__.py
mandelshtam/internal/__init__.py
mandelshtam/internal/exceptions.py
mandelshtam/internal/interfaces/__init__.py
mandelshtam/internal/interfaces/backend.py
mandelshtam/internal/interfaces/distance.py
mandelshtam/internal/levenshtein/__init__.py
mandelshtam/internal/levenshtein/backend.py
mandelshtam/internal/levenshtein/clang.c
mandelshtam/internal/levenshtein/clang.pyi
mandelshtam/internal/levenshtein/python.py
mandelshtam/internal/levenshtein/python.pyi
mandelshtam/py.typed
mandelshtam/internal/levenshtein/clang.cpython-312-darwin.so
mandelshtam-0.0.0.dist-info/AUTHORS
mandelshtam-0.0.0.dist-info/LICENSE
mandelshtam-0.0.0.dist-info/METADATA
mandelshtam-0.0.0.dist-info/WHEEL
mandelshtam-0.0.0.dist-info/RECORD
