Metadata-Version: 2.3
Name: mandelshtam
Version: 0.0.0
Summary: String similarity algorithms. Levenshtein, and more.
License: MIT
Keywords: levenshtein,python,string
Author: Sergei Y. Bogdanov
Author-email: syubogdanov@outlook.com
Maintainer: Sergei Y. Bogdanov
Maintainer-email: syubogdanov@outlook.com
Requires-Python: >=3.9,<3.14
Classifier: Development Status :: 2 - Pre-Alpha
Classifier: Intended Audience :: Developers
Classifier: Intended Audience :: Science/Research
Classifier: License :: OSI Approved :: MIT License
Classifier: Operating System :: OS Independent
Classifier: Programming Language :: Python
Classifier: Programming Language :: Python :: 3
Classifier: Programming Language :: Python :: 3.9
Classifier: Programming Language :: Python :: 3.10
Classifier: Programming Language :: Python :: 3.11
Classifier: Programming Language :: Python :: 3.12
Classifier: Programming Language :: Python :: 3.13
Classifier: Topic :: Text Processing
Classifier: Topic :: Text Processing :: General
Project-URL: Documentation, https://mandelshtam.readthedocs.io
Project-URL: Homepage, https://github.com/syubogdanov/mandelshtam
Project-URL: Repository, https://github.com/syubogdanov/mandelshtam
